napari_czann_segment/__init__.py
napari_czann_segment/_sample_data.py
napari_czann_segment/_version.py
napari_czann_segment/_widget.py
napari_czann_segment/dock_widget.py
napari_czann_segment/get_testdata.py
napari_czann_segment/napari.yaml
napari_czann_segment/onnx_inference.py
napari_czann_segment/predict.py
napari_czann_segment/process_nd.py
napari_czann_segment/utils.py
napari_czann_segment/_data/LowSNR_s001.png
napari_czann_segment/_data/PGC_20X.czi
napari_czann_segment/_data/__init__.py
napari_czann_segment/_tests/__init__.py
napari_czann_segment/_tests/test_czann_segment.py
napari_czann_segment/_tests/test_dock_widget.py
napari_czann_segment-0.0.20.dist-info/licenses/LICENSE
napari_czann_segment-0.0.20.dist-info/METADATA
napari_czann_segment-0.0.20.dist-info/WHEEL
napari_czann_segment-0.0.20.dist-info/entry_points.txt
napari_czann_segment-0.0.20.dist-info/top_level.txt
napari_czann_segment-0.0.20.dist-info/RECORD
