Metadata-Version: 2.4
Name: napari-czann-segment
Version: 0.0.20
Summary: Semantic Segmentation and Image processing using Deep Learning ONNX models packaged as *.czann files
Home-page: https://github.com/sebi06/napari-czann-segment
Author: Sebastian Rhode
Author-email: sebrhode@gmail.com
License: BSD-3-Clause
Project-URL: Bug Tracker, https://github.com/sebi06/napari-czann-segment/issues
Project-URL: Documentation, https://github.com/sebi06/napari-czann-segment#README.md
Project-URL: Source Code, https://github.com/sebi06/napari-czann-segment
Project-URL: User Support, https://github.com/sebi06/napari-czann-segment/issues
Classifier: Development Status :: 3 - Alpha
Classifier: Framework :: napari
Classifier: Intended Audience :: Developers
Classifier: Intended Audience :: Science/Research
Classifier: License :: OSI Approved :: BSD License
Classifier: Operating System :: Unix
Classifier: Operating System :: Microsoft :: Windows
Classifier: Programming Language :: Python
Classifier: Programming Language :: Python :: 3
Classifier: Programming Language :: Python :: 3 :: Only
Classifier: Programming Language :: Python :: 3.10
Classifier: Programming Language :: Python :: 3.11
Classifier: Topic :: Scientific/Engineering :: Image Processing
Requires-Python: >=3.10
License-File: LICENSE
Requires-Dist: numpy
Requires-Dist: magicgui
Requires-Dist: qtpy
Requires-Dist: napari
Requires-Dist: cztile
Requires-Dist: czmodel[pytorch]>=5
Requires-Dist: onnxruntime-gpu
Requires-Dist: bioio
Requires-Dist: bioio-ome-tiff
Requires-Dist: bioio-imageio
Requires-Dist: pytest
Requires-Dist: tiler
Requires-Dist: ryomen
Provides-Extra: testing
Requires-Dist: tox; extra == "testing"
Requires-Dist: pytest; extra == "testing"
Requires-Dist: pytest-cov; extra == "testing"
Requires-Dist: pytest-qt; extra == "testing"
Requires-Dist: napari; extra == "testing"
Requires-Dist: pyqt5; extra == "testing"
Requires-Dist: bioio; extra == "testing"
Requires-Dist: bioio-ome-tiff; extra == "testing"
Requires-Dist: bioio-imageio; extra == "testing"
Requires-Dist: tyler; extra == "testing"
Requires-Dist: ryomen; extra == "testing"
Dynamic: license-file
